<text xmlns="http://www.tei-c.org/ns/1.0" xml:id="tc"><body><div><pb facs="#f158"/>
<ab>
<lb/>om groen Papier te maeken
<lb/>Nemt het groen van siederi het jeugdigste al de rebben
<lb/>uyt gedaen dan gestampt in Mortier dan uyt
<lb/>gevrongen en dan wederom gestampt toe drye mal
<lb/>toe, nemt dan spaens groen en doet het in het sop
<lb/>tot dat het gesmoltens is, doet daer soo veele in als
<lb/>dat het ue wilt groene hebben hoe meer groen hoe
<lb/>ooger couleur ook een weinig wijn steen van tyd
<lb/>tot tyd roeren tot dat het heel gesmolten is, nemt
<lb/>dan het papier en legt het op een tafel of bert, nemt
<lb/>dan een schilder c[ou]s[t]elken en strick het daer over
<lb/>den eenen kant gedaen sijnde ank het te drogen
<lb/>en wel droge synde doet dan en anderen kant en
<lb/>dat soo dikmals tot dat het groene genoeg is
<lb/>volgens ue gouste d nemt dan wit van eyeren en
<lb/>strikt het daer over om den glans te geven als
<lb/>het wel drooge is
</ab>

</div></body></text>